quart_minify/__init__.py
quart_minify/minify.py
quart_minify-0.4.1.dist-info/LICENSE
quart_minify-0.4.1.dist-info/LICENSE.txt
quart_minify-0.4.1.dist-info/METADATA
quart_minify-0.4.1.dist-info/WHEEL
quart_minify-0.4.1.dist-info/RECORD
