Metadata-Version: 2.1
Name: quart_minify
Version: 0.4.1
Summary: A Quart extension to minify quart response for html, javascript, css and less compilation as well.
Home-page: https://github.com/AceFire6/quart_minify
License: MIT
Keywords: quart,minify
Author: Jethro Muller
Author-email: git@jethromuller.co.za
Requires-Python: >=3.7
Classifier: License :: OSI Approved :: MIT License
Classifier: Programming Language :: Python :: 3
Classifier: Programming Language :: Python :: 3.7
Classifier: Programming Language :: Python :: 3.8
Classifier: Programming Language :: Python :: 3.9
Classifier: Programming Language :: Python :: 3.10
Classifier: Programming Language :: Python :: 3.11
Classifier: Programming Language :: Python :: 3.12
Requires-Dist: htmlmin (>=0.1.12)
Requires-Dist: jsmin (>=3.0.1)
Requires-Dist: lesscpy (>=0.13.0)
Requires-Dist: quart (>=0.10.0)
Project-URL: Repository, https://github.com/AceFire6/quart_minify
